yt_transcribe/__init__.py
yt_transcribe/extractor.py
yt_transcribe/transcriber.py
yt_transcribe/utils.py
yt_transcribe-0.1.2.dist-info/METADATA
yt_transcribe-0.1.2.dist-info/WHEEL
yt_transcribe-0.1.2.dist-info/RECORD
