Metadata-Version: 2.4
Name: yt-transcribe
Version: 0.1.2
Summary: Youtube Transcript Extract and Transcribe
Project-URL: repository, https://github.com/hoishing/yt-transcribe
Author-email: Kelvin Ng <hoishing@gmail.com>
Requires-Python: >=3.12
Requires-Dist: groq>=0.18.0
Requires-Dist: python-dotenv>=1.0.1
Requires-Dist: pytubefix>=8.12.2
Requires-Dist: youtube-transcript-api>=0.6.3
